setup.cfg
setup.py
src/yahs.py
src/yahs.egg-info/PKG-INFO
src/yahs.egg-info/SOURCES.txt
src/yahs.egg-info/dependency_links.txt
src/yahs.egg-info/top_level.txt